jumpstarter_kubernetes/__init__.py
jumpstarter_kubernetes/clients.py
jumpstarter_kubernetes/clients_test.py
jumpstarter_kubernetes/cluster.py
jumpstarter_kubernetes/cluster_test.py
jumpstarter_kubernetes/datetime.py
jumpstarter_kubernetes/exporters.py
jumpstarter_kubernetes/exporters_test.py
jumpstarter_kubernetes/install.py
jumpstarter_kubernetes/json.py
jumpstarter_kubernetes/leases.py
jumpstarter_kubernetes/list.py
jumpstarter_kubernetes/py.typed
jumpstarter_kubernetes/serialize.py
jumpstarter_kubernetes/test_leases.py
jumpstarter_kubernetes/util/__init__.py
jumpstarter_kubernetes/util/async_custom_object_api.py
jumpstarter_kubernetes-0.7.4.dist-info/METADATA
jumpstarter_kubernetes-0.7.4.dist-info/WHEEL
jumpstarter_kubernetes-0.7.4.dist-info/RECORD
