Metadata-Version: 2.4
Name: jumpstarter-kubernetes
Version: 0.7.4
Project-URL: Homepage, https://jumpstarter.dev
Project-URL: source_archive, https://github.com/jumpstarter-dev/repo/archive/c5d38de69eadbb8eb0388bcfe3430a679fff0059.zip
Author-email: Kirk Brauer <kbrauer@hatci.com>
License-Expression: Apache-2.0
Requires-Python: >=3.11
Requires-Dist: jumpstarter==0.7.4
Requires-Dist: kubernetes-asyncio>=31.1.0
Requires-Dist: kubernetes>=31.0.0
Requires-Dist: pydantic>=2.8.2
